CHANGES.rst
LICENSE
MANIFEST.in
README.rst
VERSION
dev-requirements.txt
setup.py
tox.ini
daybed/__init__.py
daybed/events.py
daybed/indexer.py
daybed/permissions.py
daybed/renderers.py
daybed/tokens.py
daybed.egg-info/PKG-INFO
daybed.egg-info/SOURCES.txt
daybed.egg-info/dependency_links.txt
daybed.egg-info/entry_points.txt
daybed.egg-info/not-zip-safe
daybed.egg-info/requires.txt
daybed.egg-info/top_level.txt
daybed/backends/__init__.py
daybed/backends/exceptions.py
daybed/backends/id_generators.py
daybed/backends/couchdb/__init__.py
daybed/backends/couchdb/views.py
daybed/backends/memory/__init__.py
daybed/backends/redis/__init__.py
daybed/schemas/__init__.py
daybed/schemas/base.py
daybed/schemas/geom.py
daybed/schemas/json.py
daybed/schemas/list.py
daybed/schemas/object.py
daybed/schemas/relations.py
daybed/schemas/validators.py
daybed/tests/__init__.py
daybed/tests/spore_validation.rx
daybed/tests/support.py
daybed/tests/test_backend.py
daybed/tests/test_functional.py
daybed/tests/test_id_generators.py
daybed/tests/test_indexer.py
daybed/tests/test_permissions.py
daybed/tests/test_renderers.py
daybed/tests/test_schemas.py
daybed/tests/test_schemas_base.py
daybed/tests/test_schemas_geom.py
daybed/tests/test_schemas_json.py
daybed/tests/test_schemas_list.py
daybed/tests/test_schemas_object.py
daybed/tests/test_schemas_relations.py
daybed/tests/test_schemas_validators.py
daybed/tests/test_views.py
daybed/views/__init__.py
daybed/views/errors.py
daybed/views/fields.py
daybed/views/hello.py
daybed/views/models.py
daybed/views/records.py
daybed/views/search.py
daybed/views/spore.py
daybed/views/tokens.py