Metadata-Version: 1.1
Name: daybed
Version: 1.1.0
Summary: Form validation and data storage API.
Home-page: https://daybed.readthedocs.org/
Author: Spiral Project
Author-email: spiral-project@lolnet.org
License: BSD
Keywords: web cornice couchdb colander pyramid pylons api form angular backbone storage
Platform: UNKNOWN
Classifier: Development Status :: 4 - Beta
Classifier: License :: OSI Approved :: BSD License
Classifier: Programming Language :: Python :: 2.7
Classifier: Programming Language :: Python :: 2.6
Classifier: Topic :: Internet :: WWW/HTTP
Classifier: Topic :: Internet :: WWW/HTTP :: WSGI :: Application
Classifier: Framework :: Pyramid
